issabel_client/__init__.py
issabel_client/client.py
issabel_client-0.1.0.dist-info/licenses/LICENSE
issabel_client-0.1.0.dist-info/METADATA
issabel_client-0.1.0.dist-info/WHEEL
issabel_client-0.1.0.dist-info/top_level.txt
issabel_client-0.1.0.dist-info/RECORD
