Metadata-Version: 2.4
Name: issabel_client
Version: 0.1.0
Summary: A simple Python Client for the Issabel PBX API
Author-email: Tulio Amancio <root@tsuriu.com>
License: MIT
Project-URL: Homepage, https://github.com/tsuriu/issabel_client
Project-URL: Repository, https://github.com/tsuriu/issabel_client
Project-URL: Issues, https://github.com/tsuriu/issabel_client/issues
Keywords: issabel,pbx,api,client,python-client,asterisk,telephony
Classifier: Development Status :: 4 - Beta
Classifier: Intended Audience :: Developers
Classifier: License :: OSI Approved :: MIT License
Classifier: Programming Language :: Python :: 3
Classifier: Programming Language :: Python :: 3.7
Classifier: Programming Language :: Python :: 3.8
Classifier: Programming Language :: Python :: 3.9
Classifier: Programming Language :: Python :: 3.10
Classifier: Programming Language :: Python :: 3.11
Classifier: Topic :: Communications :: Telephony
Classifier: Topic :: Software Development :: Libraries :: Python Modules
Requires-Python: >=3.7
License-File: LICENSE
Requires-Dist: requests>=2.25.0
Provides-Extra: dev
Requires-Dist: pytest>=7.0.0; extra == "dev"
Requires-Dist: build>=1.0.0; extra == "dev"
Requires-Dist: twine>=4.0.0; extra == "dev"
Requires-Dist: black>=23.0.0; extra == "dev"
Requires-Dist: flake8>=6.0.0; extra == "dev"
Dynamic: license-file
